{
  "source": "Isaac Sim logical robot execution",
  "source_task_json": "D:\\isaac_projects\\yolo_task_execution_log.json",
  "robot_path": "/World/TrashBotRobot",
  "note": "This is logical pick-and-place animation. It does not use physical gripper contact or IK.",
  "records": [
    {
      "execution_order": 1,
      "task_id": "task_005",
      "raw_class_name": "drugbox",
      "garbage_category": "hazardous",
      "garbage_category_cn": "有害垃圾",
      "target_bin": "bin_hazardous_red",
      "target_bin_cn": "红色有害垃圾桶",
      "confidence": 0.9558,
      "action_code": 2,
      "object_prim": "/World/TrashSortingScene/trash_medicine_box",
      "bin_prim": "/World/TrashSortingScene/bin_hazardous_red",
      "status": "success",
      "grasp_success": true,
      "placement_success": true,
      "target_bin_correct": true,
      "end_to_end_success": true,
      "duration_sec": 2.147
    },
    {
      "execution_order": 2,
      "task_id": "task_010",
      "raw_class_name": "battery",
      "garbage_category": "hazardous",
      "garbage_category_cn": "有害垃圾",
      "target_bin": "bin_hazardous_red",
      "target_bin_cn": "红色有害垃圾桶",
      "confidence": 0.7916,
      "action_code": 2,
      "object_prim": "/World/TrashSortingScene/trash_battery",
      "bin_prim": "/World/TrashSortingScene/bin_hazardous_red",
      "status": "success",
      "grasp_success": true,
      "placement_success": true,
      "target_bin_correct": true,
      "end_to_end_success": true,
      "duration_sec": 2.171
    },
    {
      "execution_order": 3,
      "task_id": "task_001",
      "raw_class_name": "potato",
      "garbage_category": "kitchen",
      "garbage_category_cn": "厨余垃圾",
      "target_bin": "bin_kitchen_green",
      "target_bin_cn": "绿色厨余垃圾桶",
      "confidence": 0.97,
      "action_code": 3,
      "object_prim": "/World/TrashSortingScene/trash_apple_core",
      "bin_prim": "/World/TrashSortingScene/bin_kitchen_green",
      "status": "success",
      "grasp_success": true,
      "placement_success": true,
      "target_bin_correct": true,
      "end_to_end_success": true,
      "duration_sec": 2.153
    },
    {
      "execution_order": 4,
      "task_id": "task_008",
      "raw_class_name": "potatocut",
      "garbage_category": "kitchen",
      "garbage_category_cn": "厨余垃圾",
      "target_bin": "bin_kitchen_green",
      "target_bin_cn": "绿色厨余垃圾桶",
      "confidence": 0.8891,
      "action_code": 3,
      "object_prim": "/World/TrashSortingScene/trash_banana_peel",
      "bin_prim": "/World/TrashSortingScene/bin_kitchen_green",
      "status": "success",
      "grasp_success": true,
      "placement_success": true,
      "target_bin_correct": true,
      "end_to_end_success": true,
      "duration_sec": 2.087
    },
    {
      "execution_order": 5,
      "task_id": "task_003",
      "raw_class_name": "paper",
      "garbage_category": "recyclable",
      "garbage_category_cn": "可回收垃圾",
      "target_bin": "bin_recyclable_blue",
      "target_bin_cn": "蓝色可回收垃圾桶",
      "confidence": 0.964,
      "action_code": 1,
      "object_prim": "/World/TrashSortingScene/trash_tissue",
      "bin_prim": "/World/TrashSortingScene/bin_recyclable_blue",
      "status": "success",
      "grasp_success": true,
      "placement_success": true,
      "target_bin_correct": true,
      "end_to_end_success": true,
      "duration_sec": 2.094
    },
    {
      "execution_order": 6,
      "task_id": "task_004",
      "raw_class_name": "can",
      "garbage_category": "recyclable",
      "garbage_category_cn": "可回收垃圾",
      "target_bin": "bin_recyclable_blue",
      "target_bin_cn": "蓝色可回收垃圾桶",
      "confidence": 0.9635,
      "action_code": 1,
      "object_prim": "/World/TrashSortingScene/trash_can",
      "bin_prim": "/World/TrashSortingScene/bin_recyclable_blue",
      "status": "success",
      "grasp_success": true,
      "placement_success": true,
      "target_bin_correct": true,
      "end_to_end_success": true,
      "duration_sec": 2.112
    },
    {
      "execution_order": 7,
      "task_id": "task_006",
      "raw_class_name": "paper",
      "garbage_category": "recyclable",
      "garbage_category_cn": "可回收垃圾",
      "target_bin": "bin_recyclable_blue",
      "target_bin_cn": "蓝色可回收垃圾桶",
      "confidence": 0.9509,
      "action_code": 1,
      "object_prim": "/World/TrashSortingScene/trash_paper_box",
      "bin_prim": "/World/TrashSortingScene/bin_recyclable_blue",
      "status": "success",
      "grasp_success": true,
      "placement_success": true,
      "target_bin_correct": true,
      "end_to_end_success": true,
      "duration_sec": 2.092
    },
    {
      "execution_order": 8,
      "task_id": "task_007",
      "raw_class_name": "bottle",
      "garbage_category": "recyclable",
      "garbage_category_cn": "可回收垃圾",
      "target_bin": "bin_recyclable_blue",
      "target_bin_cn": "蓝色可回收垃圾桶",
      "confidence": 0.9358,
      "action_code": 1,
      "object_prim": "/World/TrashSortingScene/trash_plastic_bottle",
      "bin_prim": "/World/TrashSortingScene/bin_recyclable_blue",
      "status": "success",
      "grasp_success": true,
      "placement_success": true,
      "target_bin_correct": true,
      "end_to_end_success": true,
      "duration_sec": 2.101
    },
    {
      "execution_order": 9,
      "task_id": "task_009",
      "raw_class_name": "bottle",
      "garbage_category": "recyclable",
      "garbage_category_cn": "可回收垃圾",
      "target_bin": "bin_recyclable_blue",
      "target_bin_cn": "蓝色可回收垃圾桶",
      "confidence": 0.8364,
      "action_code": 1,
      "object_prim": "/World/TrashSortingScene/trash_dirty_bottle",
      "bin_prim": "/World/TrashSortingScene/bin_recyclable_blue",
      "status": "success",
      "grasp_success": true,
      "placement_success": true,
      "target_bin_correct": true,
      "end_to_end_success": true,
      "duration_sec": 2.22
    },
    {
      "execution_order": 10,
      "task_id": "task_002",
      "raw_class_name": "papercup",
      "garbage_category": "other",
      "garbage_category_cn": "其他垃圾",
      "target_bin": "bin_other_gray",
      "target_bin_cn": "灰色其他垃圾桶",
      "confidence": 0.9652,
      "action_code": 4,
      "object_prim": "/World/TrashSortingScene/trash_broken_cup",
      "bin_prim": "/World/TrashSortingScene/bin_other_gray",
      "status": "success",
      "grasp_success": true,
      "placement_success": true,
      "target_bin_correct": true,
      "end_to_end_success": true,
      "duration_sec": 2.131
    }
  ],
  "metrics": {
    "num_tasks": 10,
    "grasp_success_rate": 1.0,
    "placement_success_rate": 1.0,
    "target_bin_accuracy": 1.0,
    "end_to_end_success_rate": 1.0,
    "average_duration_sec": 2.1308,
    "category_count": {
      "hazardous": 2,
      "kitchen": 2,
      "recyclable": 5,
      "other": 1
    },
    "target_bin_count": {
      "bin_hazardous_red": 2,
      "bin_kitchen_green": 2,
      "bin_recyclable_blue": 5,
      "bin_other_gray": 1
    },
    "status_count": {
      "success": 10
    }
  }
}